README.rst
setup.py
orgtup/__init__.py
orgtup.egg-info/PKG-INFO
orgtup.egg-info/SOURCES.txt
orgtup.egg-info/dependency_links.txt
orgtup.egg-info/pbr.json
orgtup.egg-info/top_level.txt
orgtup.egg-info/zip-safe