Metadata-Version: 1.0
Name: orgtup
Version: 1.2.0
Summary: Named tuples related to common services
Home-page: https://github.com/nicholasbishop/orgtup
Author: Nicholas Bishop
Author-email: nicholasbishop@gmail.com
License: MIT
Platform: UNKNOWN
